[
	{
	"name": "Кредитная Карта - хочукуплю",
	"price_info": "От 2% До 1 100 000 руб",
    "image_url": "https://raw.githubusercontent.com/vrsstudio/img/main/genbankruu.png",
    "sum": "400 - 15 000",
	"term": "2 года",
	"percent": "1,50% - 1,85%",
    "url": "https://www.genbank.ru/chastnym-litsam/cards/moya-kreditnaya-karta/?utm_referrer=https%3A%2F%2Fwww.google.com%2F",
    "text": "<p>Новый повышенный кэшбэк 5% на бытовую технику, электронику, одежду и обувь</p><p>Кредитный лимит до 300 000 руб.</p>"
  },
  {
	"name": "Альфа банк",
	"price_info": "От 3% До 950 000 руб",
    "image_url": "https://raw.githubusercontent.com/vrsstudio/img/main/AlfBank.png",
    "sum": "400 - 15 000",
	"term": "3 года",
	"percent": "1,50% - 1,85%",
    "url": "https://alfabank.ru/everyday/debit-cards/alfacard/",
    "text": "<p>100 дней без % по кредиту на покупки и снятие наличных.</p><p>Кредитный лимит до 500 000 руб.</p>"
  },
    {
	"name": "Кредитная карта - Платинум",
	"price_info": "От 2% До 1 150 000 руб",
    "image_url": "https://raw.githubusercontent.com/vrsstudio/img/main/tbank.png",
    "sum": "400 - 15 000",
	"term": "2 года",
	"percent": "1,50% - 1,85%",
    "url": "https://www.tbank.ru/cards/credit-cards/tinkoff-platinum/?internal_source=filter_main",
    "text": "<p>Новый повышенный кэшбэк 5% на бытовую технику, электронику, одежду и обувь</p><p>Кредитный лимит до 300 000 руб.</p>"
  }
  
]
